prodigal_agents/__init__.py
prodigal_agents/agent.py
prodigal_agents/config.py
prodigal_agents/core/agent.py
prodigal_agents/runner.py
prodigal_agents/tests/test_agent.py
prodigal_agents-0.1.0.dist-info/LICENSE
prodigal_agents-0.1.0.dist-info/METADATA
prodigal_agents-0.1.0.dist-info/WHEEL
prodigal_agents-0.1.0.dist-info/RECORD
