Metadata-Version: 2.1
Name: prodigal-agents
Version: 0.1.0
Summary: Core Agent SDK for Prodigal AI
License: Apache-2.0
Author: Prodigal AI
Author-email: contact@prodigalai.com
Requires-Python: >=3.9,<4.0
Classifier: License :: OSI Approved :: Apache Software License
Classifier: Programming Language :: Python :: 3
Classifier: Programming Language :: Python :: 3.9
Classifier: Programming Language :: Python :: 3.10
Classifier: Programming Language :: Python :: 3.11
Classifier: Programming Language :: Python :: 3.12
Requires-Dist: pydantic (>=2.0,<3.0)
Requires-Dist: requests (>=2.31.0,<3.0.0)
Project-URL: Bug Tracker, https://github.com/Prodigal-AI/prodigal-agents/issues
Project-URL: Documentation, https://prodigal-agents.readthedocs.io
Project-URL: Homepage, https://github.com/Prodigal-AI/prodigal-agents
Project-URL: Repository, https://github.com/Prodigal-AI/prodigal-agents.git
